setup.py
django_shop_braintree.egg-info/PKG-INFO
django_shop_braintree.egg-info/SOURCES.txt
django_shop_braintree.egg-info/dependency_links.txt
django_shop_braintree.egg-info/requires.txt
django_shop_braintree.egg-info/top_level.txt
shop_braintree/__init__.py
shop_braintree/backends.py
shop_braintree/forms.py
shop_braintree/models.py
shop_braintree/migrations/0001_initial.py
shop_braintree/migrations/__init__.py