Metadata-Version: 1.0
Name: django-shop-braintree
Version: 0.1
Summary: A Braintree payment backend for django-shop
Home-page: http://github.com/derek-schultz/django-shop-braintree
Author: Derek Schultz
Author-email: derek@derekschultz.net
License: MIT
Platform: any
